code_quality_agent/__init__.py
code_quality_agent/__main__.py
code_quality_agent/agent.py
code_quality_agent/analyzers.py
code_quality_agent/chatbot.py
code_quality_agent/cli.py
code_quality_agent/config.py
code_quality_agent/embedding_rag.py
code_quality_agent/rag_system.py
code_quality_agent/report_generator.py
code_quality_agent/simple_embedding_rag.py
code_quality_agent/simple_rag.py
code_quality_agent/utils/__init__.py
code_quality_agent/utils/file_handler.py
code_quality_intelligence-1.6.2.dist-info/METADATA
code_quality_intelligence-1.6.2.dist-info/WHEEL
code_quality_intelligence-1.6.2.dist-info/entry_points.txt
code_quality_intelligence-1.6.2.dist-info/top_level.txt
code_quality_intelligence-1.6.2.dist-info/RECORD
