Metadata-Version: 2.4
Name: code-quality-intelligence
Version: 1.6.2
Summary: AI-powered code quality analysis tool with GitHub integration and interactive chatbot
Home-page: https://github.com/suvraadeep/Code-Quality-Intelligence-Agent
Author: Suvraadeep Das
Author-email: Suvraadeep Das <suvraadeep.das@gmail.com>
License-Expression: MIT
Project-URL: Homepage, https://github.com/suvraadeep/Code-Quality-Intelligence-Agent
Project-URL: Bug Reports, https://github.com/suvraadeep/Code-Quality-Intelligence-Agent/issues
Project-URL: Source Code, https://github.com/suvraadeep/Code-Quality-Intelligence-Agent
Project-URL: Documentation, https://github.com/suvraadeep/Code-Quality-Intelligence-Agent#readme
Keywords: code quality,static analysis,AI,LLM,security,complexity,GitHub,chatbot
Classifier: Development Status :: 5 - Production/Stable
Classifier: Intended Audience :: Developers
Classifier: Topic :: Software Development :: Quality Assurance
Classifier: Topic :: Software Development :: Testing
Classifier: Programming Language :: Python :: 3
Classifier: Programming Language :: Python :: 3.8
Classifier: Programming Language :: Python :: 3.9
Classifier: Programming Language :: Python :: 3.10
Classifier: Programming Language :: Python :: 3.11
Classifier: Programming Language :: Python :: 3.12
Classifier: Operating System :: OS Independent
Requires-Python: >=3.8
Requires-Dist: langchain==0.2.16
Requires-Dist: langchain-groq==0.1.9
Requires-Dist: langchain-community==0.2.16
Requires-Dist: click==8.1.7
Requires-Dist: rich==13.7.1
Requires-Dist: gitpython==3.1.43
Requires-Dist: requests==2.31.0
Requires-Dist: python-dotenv==1.0.1
Requires-Dist: bandit==1.7.5
Requires-Dist: radon==6.0.1
Requires-Dist: safety==3.2.7
Requires-Dist: pygments==2.17.2
Requires-Dist: pathspec==0.12.1
Requires-Dist: tqdm==4.66.2
Provides-Extra: full
Requires-Dist: streamlit==1.31.0; extra == "full"
Requires-Dist: pandas==2.2.0; extra == "full"
Requires-Dist: matplotlib==3.8.4; extra == "full"
Requires-Dist: plotly==5.19.0; extra == "full"
Requires-Dist: seaborn==0.13.2; extra == "full"
Requires-Dist: altair==5.2.0; extra == "full"
Provides-Extra: rag
Requires-Dist: chromadb==0.4.22; extra == "rag"
Requires-Dist: sentence-transformers==2.2.2; extra == "rag"
Requires-Dist: tiktoken==0.5.2; extra == "rag"
Requires-Dist: faiss-cpu==1.8.0; extra == "rag"
Provides-Extra: dev
Requires-Dist: pytest; extra == "dev"
Requires-Dist: black; extra == "dev"
Requires-Dist: flake8; extra == "dev"
Requires-Dist: mypy; extra == "dev"
Dynamic: author
Dynamic: home-page
Dynamic: requires-python
